rajveer_stt/__init__.py
soul_rajveer_stt-0.1.dist-info/METADATA
soul_rajveer_stt-0.1.dist-info/WHEEL
soul_rajveer_stt-0.1.dist-info/top_level.txt
soul_rajveer_stt-0.1.dist-info/RECORD
