Metadata-Version: 2.4
Name: SOUL_RAJVEER-STT
Version: 0.1
Summary: this is speech to text  package created by  a rajveer 
Author: Rajveer Singh Chouhan
Author-email: chouhanrajveer009@gmail.com
Dynamic: author
Dynamic: author-email
Dynamic: summary
